{
  "project_info": {
    "project_number": "569407952421",
    "project_id": "darkverseapp",
    "storage_bucket": "darkverseapp.firebasestorage.app"
  },
  "client": [
    {
      "client_info": {
        "mobilesdk_app_id": "1:569407952421:android:0e9bd222926402025111cc",
        "android_client_info": {
          "package_name": "com.darkverse.app"
        }
      },
      "oauth_client": [],
      "api_key": [
        {
          "current_key": "AIzaSyBnMwcIyu2pHdHjtntopPIskZG2NSWfKq0"
        }
      ],
      "services": {
        "appinvite_service": {
          "other_platform_oauth_client": []
        }
      }
    }
  ],
  "configuration_version": "1"
}